mcp_coze_server/__init__.py
mcp_coze_server/__main__.py
mcp_coze_server/server.py
mcp_coze_server/version.py
mcp_coze_server-0.1.12.dist-info/licenses/LICENSE
mcp_coze_server-0.1.12.dist-info/METADATA
mcp_coze_server-0.1.12.dist-info/WHEEL
mcp_coze_server-0.1.12.dist-info/entry_points.txt
mcp_coze_server-0.1.12.dist-info/top_level.txt
mcp_coze_server-0.1.12.dist-info/RECORD
