Metadata-Version: 2.4
Name: mcp-coze-server
Version: 0.1.12
Summary: A MCP server implementation for Coze API
Author-email: flink <w741069229@gmail.com>
License-Expression: MIT
Project-URL: Homepage, https://github.com/shizeying/coze-mcp-server
Project-URL: Bug Tracker, https://github.com/shizeying/coze-mcp-server/issues
Project-URL: Documentation, https://github.com/shizeying/coze-mcp-server#readme
Project-URL: Source Code, https://github.com/shizeying/coze-mcp-server
Keywords: mcp,coze,api,server
Classifier: Development Status :: 4 - Beta
Classifier: Programming Language :: Python :: 3
Classifier: Programming Language :: Python :: 3.11
Classifier: Operating System :: OS Independent
Requires-Python: >=3.11
License-File: LICENSE
Requires-Dist: mcp>=1.6.0
Requires-Dist: pydantic>=2.0.0
Requires-Dist: cozepy-flink
Dynamic: license-file
Dynamic: requires-python
